com_vitalai_domain_nlp/__init__.py
com_vitalai_domain_nlp/domain-ontology/vital-nlp-0.2.304.owl
com_vitalai_domain_nlp/model/Abbreviation.py
com_vitalai_domain_nlp/model/Abbreviation.pyi
com_vitalai_domain_nlp/model/AbbreviationInstance.py
com_vitalai_domain_nlp/model/AbbreviationInstance.pyi
com_vitalai_domain_nlp/model/Annotation.py
com_vitalai_domain_nlp/model/Annotation.pyi
com_vitalai_domain_nlp/model/Content.py
com_vitalai_domain_nlp/model/Content.pyi
com_vitalai_domain_nlp/model/Document.py
com_vitalai_domain_nlp/model/Document.pyi
com_vitalai_domain_nlp/model/DomainOntology.py
com_vitalai_domain_nlp/model/Edge_hasAbbreviation.py
com_vitalai_domain_nlp/model/Edge_hasAbbreviation.pyi
com_vitalai_domain_nlp/model/Edge_hasAbbreviationInstance.py
com_vitalai_domain_nlp/model/Edge_hasAbbreviationInstance.pyi
com_vitalai_domain_nlp/model/Edge_hasAnnotation.py
com_vitalai_domain_nlp/model/Edge_hasAnnotation.pyi
com_vitalai_domain_nlp/model/Edge_hasCategory.py
com_vitalai_domain_nlp/model/Edge_hasCategory.pyi
com_vitalai_domain_nlp/model/Edge_hasContent.py
com_vitalai_domain_nlp/model/Edge_hasContent.pyi
com_vitalai_domain_nlp/model/Edge_hasEntity.py
com_vitalai_domain_nlp/model/Edge_hasEntity.pyi
com_vitalai_domain_nlp/model/Edge_hasEntityInstance.py
com_vitalai_domain_nlp/model/Edge_hasEntityInstance.pyi
com_vitalai_domain_nlp/model/Edge_hasEquivalenceElement.py
com_vitalai_domain_nlp/model/Edge_hasEquivalenceElement.pyi
com_vitalai_domain_nlp/model/Edge_hasEquivalenceRelationInstance.py
com_vitalai_domain_nlp/model/Edge_hasEquivalenceRelationInstance.pyi
com_vitalai_domain_nlp/model/Edge_hasEventElement.py
com_vitalai_domain_nlp/model/Edge_hasEventElement.pyi
com_vitalai_domain_nlp/model/Edge_hasEventInstance.py
com_vitalai_domain_nlp/model/Edge_hasEventInstance.pyi
com_vitalai_domain_nlp/model/Edge_hasEventTrigger.py
com_vitalai_domain_nlp/model/Edge_hasEventTrigger.pyi
com_vitalai_domain_nlp/model/Edge_hasImageReference.py
vital_ai_nlp-0.1.5.dist-info/METADATA
vital_ai_nlp-0.1.5.dist-info/WHEEL
vital_ai_nlp-0.1.5.dist-info/entry_points.txt
vital_ai_nlp-0.1.5.dist-info/top_level.txt
vital_ai_nlp-0.1.5.dist-info/RECORD
